canrevan/__init__.py
canrevan/__main__.py
canrevan/crawling.py
canrevan/parsing.py
canrevan/utils.py
canrevan-4.0.0.dist-info/LICENSE
canrevan-4.0.0.dist-info/METADATA
canrevan-4.0.0.dist-info/WHEEL
canrevan-4.0.0.dist-info/entry_points.txt
canrevan-4.0.0.dist-info/top_level.txt
canrevan-4.0.0.dist-info/RECORD
