Metadata-Version: 2.1
Name: canrevan
Version: 4.0.0
Summary: Simple Naver News Crawler
Home-page: https://github.com/affjljoo3581/canrevan
Author: Jungwoo Park
Author-email: affjljoo3581@gmail.com
License: Apache-2.0
Keywords: naver,news,dataset,nlp
Platform: UNKNOWN
Classifier: Environment :: Console
Classifier: Operating System :: OS Independent
Classifier: Programming Language :: Python :: 3
Classifier: Programming Language :: Python :: 3.6
Classifier: Programming Language :: Python :: 3.7
Classifier: Programming Language :: Python :: 3.8
Classifier: Topic :: Scientific/Engineering :: Artificial Intelligence
Requires-Python: >=3.6.0
Requires-Dist: tqdm (>=4.46.0)
Requires-Dist: bs4
Requires-Dist: lxml (>=4.5.1)
Requires-Dist: aiohttp
